docs/source/conf.py
sdypy_io_tdms/__init__.py
sdypy_io_tdms/tdms.py
tests/__init__.py
tests/test_tdms.py
sdypy_io_tdms-0.1.2.dist-info/METADATA
sdypy_io_tdms-0.1.2.dist-info/WHEEL
sdypy_io_tdms-0.1.2.dist-info/top_level.txt
sdypy_io_tdms-0.1.2.dist-info/RECORD
