Metadata-Version: 2.4
Name: sdypy_io_tdms
Version: 0.1.2
Summary: TDMS file read and write functions compliant with SDyPy SEP5
Author-email: Wout Weijtjens <wout.weijtjens@vub.be>
Maintainer-email: Wout Weijtjens <wout.weijtjens@vub.be>
License: MIT license
Keywords: io,tdms,SEP5
Classifier: Development Status :: 3 - Alpha
Classifier: Intended Audience :: Developers
Classifier: Programming Language :: Python :: 3.6
Requires-Python: >=3.6
Requires-Dist: numpy>=1.11.0
Requires-Dist: nptdms>=1.3.0
Requires-Dist: sdypy-sep005>=0.1.0
Requires-Dist: pytz
